BeginnersbookCYuyanJiaochengChuyiFix1/README.md
BeginnersbookCYuyanJiaochengChuyiFix1/__init__.py
BeginnersbookCYuyanJiaochengChuyiFix1/__main__.py
BeginnersbookCYuyanJiaochengChuyiFix1/file.epub
BeginnersbookCYuyanJiaochengChuyiFix1/index.html
BeginnersbookCYuyanJiaochengChuyiFix1/css/__init__.py
BeginnersbookCYuyanJiaochengChuyiFix1/css/annotations.css
BeginnersbookCYuyanJiaochengChuyiFix1/css/main.css
BeginnersbookCYuyanJiaochengChuyiFix1/css/normalize.css
BeginnersbookCYuyanJiaochengChuyiFix1/css/popup.css
BeginnersbookCYuyanJiaochengChuyiFix1/font/__init__.py
BeginnersbookCYuyanJiaochengChuyiFix1/font/fontello.eot
BeginnersbookCYuyanJiaochengChuyiFix1/font/fontello.svg
BeginnersbookCYuyanJiaochengChuyiFix1/font/fontello.ttf
BeginnersbookCYuyanJiaochengChuyiFix1/font/fontello.woff
BeginnersbookCYuyanJiaochengChuyiFix1/img/__init__.py
BeginnersbookCYuyanJiaochengChuyiFix1/img/annotator-glyph-sprite.png
BeginnersbookCYuyanJiaochengChuyiFix1/img/annotator-icon-sprite.png
BeginnersbookCYuyanJiaochengChuyiFix1/img/apple-touch-icon.png
BeginnersbookCYuyanJiaochengChuyiFix1/img/cancelfullscreen.png
BeginnersbookCYuyanJiaochengChuyiFix1/img/close.png
BeginnersbookCYuyanJiaochengChuyiFix1/img/fullscreen.png
BeginnersbookCYuyanJiaochengChuyiFix1/img/loader.gif
BeginnersbookCYuyanJiaochengChuyiFix1/img/menu-icon.png
BeginnersbookCYuyanJiaochengChuyiFix1/img/save.png
BeginnersbookCYuyanJiaochengChuyiFix1/img/saved.png
BeginnersbookCYuyanJiaochengChuyiFix1/img/settings-s.png
BeginnersbookCYuyanJiaochengChuyiFix1/img/settings.png
BeginnersbookCYuyanJiaochengChuyiFix1/img/star.png
BeginnersbookCYuyanJiaochengChuyiFix1/js/__init__.py
BeginnersbookCYuyanJiaochengChuyiFix1/js/epub.js
BeginnersbookCYuyanJiaochengChuyiFix1/js/epub.min.js
BeginnersbookCYuyanJiaochengChuyiFix1/js/epub.min.map
BeginnersbookCYuyanJiaochengChuyiFix1/js/hooks.min.js
BeginnersbookCYuyanJiaochengChuyiFix1/js/hooks.min.map
BeginnersbookCYuyanJiaochengChuyiFix1/js/reader.js
beginnersbook_c_yuyan_jiaocheng_chuyi_fix1-2025.3.23.0.dist-info/METADATA
beginnersbook_c_yuyan_jiaocheng_chuyi_fix1-2025.3.23.0.dist-info/WHEEL
beginnersbook_c_yuyan_jiaocheng_chuyi_fix1-2025.3.23.0.dist-info/entry_points.txt
beginnersbook_c_yuyan_jiaocheng_chuyi_fix1-2025.3.23.0.dist-info/top_level.txt
beginnersbook_c_yuyan_jiaocheng_chuyi_fix1-2025.3.23.0.dist-info/RECORD
